{
  "Individual filtering statistics": {
    "standard_headers": {
      "Headers into filter": 4677,
      "Headers removed": 4215
    },
    "third_party": {
      "Headers into filter": 4677,
      "Headers removed": 576
    },
    "min_length": {
      "Headers into filter": 4677,
      "Headers removed": 1582
    },
    "inconsistent": {
      "Headers into filter": 4677,
      "Headers removed": 2304
    },
    "not_in_storage": {
      "Headers into filter": 4677,
      "Headers removed": 4215
    }
  }
}